[
  {
    "call": "square_resource",
    "arguments": {
      "name": "muzzle_flash_0_3d",
      "texture_filename": "#muzzle_flash_3d",
      "min": [-1, -1],
      "max": [1, 1],
      "center_distances": [0, 501],
      "occluded_pass": "none",
      "occluder_pass": "none",
      "emissive": [1, 1, 1],
      "ambient": [0, 0, 0],
      "blend_mode": "continuous",
      "alpha_distances": [0, 0, "inf", "inf"],
      "cull_faces": true,
      "aggregate_mode": "none",
      "transformation_mode": "position_flat",
      "fog_distances": "%fog_distances",
      "fog_ambient": "%fog_ambient",
      "billboards": [
        {"uv_scale": [0.5, 0.5], "uv_offset": [0  , 0], "vertex_scale": [0.15, 0.15, 1], "alpha_distances": [0, 0, 250, 400], "max_center_distance": 503, "occluder_pass": "none"},
        {"uv_scale": [0.5, 0.5], "uv_offset": [0.5, 0], "vertex_scale": [0.15, 0.15, 1], "alpha_distances": [0, 0, 250, 400], "max_center_distance": 503, "occluder_pass": "none"}
      ]
    }
  },
  {
    "call": "animatable_billboards",
    "arguments": {
      "name": "animatable_muzzle_flash_0_3d",
      "billboards": "muzzle_flash_0_3d",
      "max_num_instances": 10000,
      "type": "smoke"
    }
  },
  {
    "call": "animated_billboards",
    "arguments": {
      "name": "muzzle_flash_0_3d_orange_brown",
      "animatable": "animatable_muzzle_flash_0_3d",
      "frames": [0],
      "final_texture_w": 1,
      "duration": 0.1
    }
  }
]
