[
  {
    "call": "add_texture_atlas",
    "arguments": {
      "name": "vegetation0",
      "width": 4096,
      "height": 2048,
      "color_mode": "rgba",
      "images": [
        {"target_position":[0, 0], "texture": "textures/proctree/one_24/out-1-5.png"},
        {"target_position":[1024, 0], "texture": "textures/proctree/one_24/out-2-5.png"},
        {"target_position":[2048, 0], "texture": "textures/proctree/one/out-3-5.png"},
        {"target_position":[0, 1024], "texture": "textures/proctree/one/out-4-5.png"},
        {"target_position":[1024, 1024], "texture": "textures/proctree/one_large/out-1-10.png"},
        {"target_position":[2048, 1024], "texture": "textures/proctree/one_large/out-2-10.png"}
      ]
    }
  },
  {
    "comment": {
      "call": "save_texture_png",
      "arguments": {
        "name": "vegetation0",
        "filename": "/tmp/vegetation0.png",
        "color_mode": "rgba"
      }
    }
  },
  {
    "call": "add_texture_descriptor",
    "arguments": {
      "name": "vegetation0",
      "color": "#vegetation0",
      "color_mode": "rgba",
      "anisotropic_filtering_level": 16,
      "wrap_mode_s": "clamp_to_edge",
      "wrap_mode_t": "clamp_to_edge"
    }
  },
  {
    "call": "square_resource",
    "arguments": {
      "name": "vegetation0",
      "texture_filename": "#vegetation0",
      "min": [-0.5, 0],
      "max": [0.5, 1],
      "occluded_pass": "lightmap_blobs",
      "occluder_pass": "lightmap_black_global_and_local",
      "ambient": [1, 1, 1],
      "blend_mode": "semi_continuous_02",
      "alpha_distances": [0, 0, "inf", "inf"],
      "cull_faces": true,
      "aggregate_mode": "instances_sorted",
      "transformation_mode": "position_lookat",
      "fog_distances": "%FOG_DISTANCES",
      "fog_ambient": "%FOG_AMBIENT",
      "billboards": [
        {"uv_scale": [0.25 , 0.5 ], "uv_offset":[0    , 0  ], "vertex_scale": [10  ,10  , 1], "alpha_distances": [0, 0, 450, 600], "max_center_distance": 750, "occluder_pass": "lightmap_black_global_and_local"},
        {"uv_scale": [0.25 , 0.5 ], "uv_offset":[0.25 , 0  ], "vertex_scale": [10  ,10  , 1], "alpha_distances": [0, 0, 450, 600], "max_center_distance": 750, "occluder_pass": "lightmap_black_global_and_local"},
        {"uv_scale": [0.25 , 0.5 ], "uv_offset":[0.5  , 0  ], "vertex_scale": [10  ,10  , 1], "alpha_distances": [0, 0, 450, 600], "max_center_distance": 750, "occluder_pass": "lightmap_black_global_and_local"},
        {"uv_scale": [0.25 , 0.5 ], "uv_offset":[0    , 0.5], "vertex_scale": [10  ,10  , 1], "alpha_distances": [0, 0, 450, 600], "max_center_distance": 750, "occluder_pass": "lightmap_black_global_and_local"},
        {"uv_scale": [0.25 , 0.5 ], "uv_offset":[0.25 , 0.5], "vertex_scale": [15  ,15  , 1], "alpha_distances": [0, 0, 450, 600], "max_center_distance": 750, "occluder_pass": "lightmap_black_global_and_local"},
        {"uv_scale": [0.25 , 0.5 ], "uv_offset":[0.5  , 0.5], "vertex_scale": [15  ,15  , 1], "alpha_distances": [0, 0, 450, 600], "max_center_distance": 750, "occluder_pass": "lightmap_black_global_and_local"}
      ]
    }
  }
]
