{
    "configurations": [
        {
            "name": "Linux",
            "includePath": [
                "${workspaceFolder}/Mlib",
                "${workspaceFolder}/Mlib/cereal/include",
                "${workspaceFolder}/Mlib/eve/include",
                "${workspaceFolder}/Mlib/recastnavigation/Recast/Include",
                "${workspaceFolder}/Mlib/recastnavigation/Detour/Include",
                "${workspaceFolder}/Mlib/recastnavigation/DetourCrowd/Include",
                "${workspaceFolder}/Mlib/recastnavigation/DebugUtils/Include",
                "/usr/include/AL",
                "/usr/local/include/opencv4",
                "/usr/include/SDL2"
            ],
            "defines": [],
            "compilerPath": "/usr/bin/clang++-20",
            "cppStandard": "c++23",
            "intelliSenseMode": "linux-clang-x64",
            "compilerArgs": ["-Wall", "-Wno-unknown-pragmas", "-Wmismatched-tags", "-Wconversion", "-Werror"]
        },
        {
            "name": "Android",
            "includePath": [
                "${workspaceFolder}/Mlib",
                "${workspaceFolder}/Mlib/cereal/include",
                "${workspaceFolder}/Mlib/recastnavigation/DebugUtils/Include",
                "${workspaceFolder}/Mlib/recastnavigation/Detour/Include",
                "${workspaceFolder}/Mlib/recastnavigation/Recast/Include",
                "/usr/include/AL",
                "/opt/AndroidSdk/ndk/30.0.14904198/toolchains/llvm/prebuilt/linux-x86_64/sysroot/usr/include",
                "/opt/AndroidSdk/ndk/30.0.14904198/sources/android/native_app_glue"
            ],
            "defines": ["WITHOUT_LAME"],
            "compilerPath": "/opt/AndroidSdk/ndk/30.0.14904198/toolchains/llvm/prebuilt/linux-x86_64/bin/clang++",
            "cppStandard": "c++23",
            "intelliSenseMode": "linux-clang-x64",
            "compilerArgs": ["-Wall", "-Wno-unknown-pragmas", "-Wmismatched-tags", "-Wconversion", "-Werror"]
        },
        {
            "name": "MSYS2",
            "includePath": [
                "${workspaceFolder}\\Mlib",
                "D:\\Programs\\msys64\\mingw64\\include\\c++\\10.3.0",
                "D:\\Programs\\msys64\\usr\\include"
            ],
            "defines": ["_USE_MATH_DEFINES"],
            "compilerPath": "D:\\Programs\\msys64\\mingw64\\bin\\g++.exe",
            "cppStandard": "c++23",
            "intelliSenseMode": "gcc-x64"
        }
    ],
    "version": 4
}
